testrame/__init__.py
testrame/main.py
testrame/.system/imports.py
testrame/.system/index.py
testrame/.system/modules/jobs.py
testrame/.system/sources/clight.json
testrame/.system/sources/logo.ico
testrame-1.0.2.dist-info/licenses/LICENSE
testrame-1.0.2.dist-info/METADATA
testrame-1.0.2.dist-info/WHEEL
testrame-1.0.2.dist-info/entry_points.txt
testrame-1.0.2.dist-info/top_level.txt
testrame-1.0.2.dist-info/RECORD
